LICENSE.md
MANIFEST.in
README.md
pyproject.toml
setup.py
lib/hts_engine_API/src/CMakeLists.txt
lib/hts_engine_API/src/COPYING
lib/hts_engine_API/src/README
lib/hts_engine_API/src/hts_engine_API.pc.in
lib/hts_engine_API/src/bin/hts_engine.c
lib/hts_engine_API/src/include/HTS_engine.h
lib/hts_engine_API/src/lib/HTS_audio.c
lib/hts_engine_API/src/lib/HTS_engine.c
lib/hts_engine_API/src/lib/HTS_gstream.c
lib/hts_engine_API/src/lib/HTS_hidden.h
lib/hts_engine_API/src/lib/HTS_label.c
lib/hts_engine_API/src/lib/HTS_misc.c
lib/hts_engine_API/src/lib/HTS_model.c
lib/hts_engine_API/src/lib/HTS_pstream.c
lib/hts_engine_API/src/lib/HTS_sstream.c
lib/hts_engine_API/src/lib/HTS_vocoder.c
lib/open_jtalk/src/CMakeLists.txt
lib/open_jtalk/src/COPYING
lib/open_jtalk/src/README
lib/open_jtalk/src/bin/CMakeLists.txt
lib/open_jtalk/src/bin/open_jtalk.c
lib/open_jtalk/src/jpcommon/jpcommon.c
lib/open_jtalk/src/jpcommon/jpcommon.h
lib/open_jtalk/src/jpcommon/jpcommon_label.c
lib/open_jtalk/src/jpcommon/jpcommon_node.c
lib/open_jtalk/src/jpcommon/jpcommon_rule_ascii_for_euc_jp.h
lib/open_jtalk/src/jpcommon/jpcommon_rule_ascii_for_shift_jis.h
lib/open_jtalk/src/jpcommon/jpcommon_rule_ascii_for_utf_8.h
lib/open_jtalk/src/jpcommon/jpcommon_rule_euc_jp.h
lib/open_jtalk/src/jpcommon/jpcommon_rule_shift_jis.h
lib/open_jtalk/src/jpcommon/jpcommon_rule_utf_8.h
lib/open_jtalk/src/mecab/COPYING
lib/open_jtalk/src/mecab/config.h.in
lib/open_jtalk/src/mecab-naist-jdic/COPYING
lib/open_jtalk/src/mecab/src/char_property.cpp
lib/open_jtalk/src/mecab/src/char_property.h
lib/open_jtalk/src/mecab/src/common.h
lib/open_jtalk/src/mecab/src/connector.cpp
lib/open_jtalk/src/mecab/src/connector.h
lib/open_jtalk/src/mecab/src/context_id.cpp
lib/open_jtalk/src/mecab/src/context_id.h
lib/open_jtalk/src/mecab/src/darts.h
lib/open_jtalk/src/mecab/src/dictionary.cpp
lib/open_jtalk/src/mecab/src/dictionary.h
lib/open_jtalk/src/mecab/src/dictionary_compiler.cpp
lib/open_jtalk/src/mecab/src/dictionary_generator.cpp
pyopenjtalk_somniumism.egg-info/PKG-INFO
pyopenjtalk_somniumism.egg-info/SOURCES.txt
pyopenjtalk_somniumism.egg-info/dependency_links.txt
pyopenjtalk_somniumism.egg-info/requires.txt
pyopenjtalk_somniumism.egg-info/top_level.txt
