Metadata-Version: 2.4
Name: pyopenjtalk-somniumism
Version: 0.1.dev233
Summary: A python wrapper for OpenJTalk (forked with /tmp support for serverless environments)
Author: somniumism (fork maintainer)
Author-email: Ryuichi Yamamoto <zryuichi@gmail.com>
License: The pyopenjtalk package is licensed under the MIT "Expat" License:
Project-URL: Homepage, https://github.com/somniumism/pyopenjtalk
Keywords: OpenJTalk,Research,serverless,vercel,tmp
Classifier: Operating System :: POSIX
Classifier: Operating System :: Unix
Classifier: Operating System :: MacOS
Classifier: Operating System :: Microsoft :: Windows
Classifier: Programming Language :: Cython
Classifier: Programming Language :: Python
Classifier: Programming Language :: Python :: 3
Classifier: Programming Language :: Python :: 3.8
Classifier: Programming Language :: Python :: 3.9
Classifier: Programming Language :: Python :: 3.10
Classifier: License :: OSI Approved :: MIT License
Classifier: Topic :: Scientific/Engineering
Classifier: Topic :: Software Development
Classifier: Intended Audience :: Science/Research
Classifier: Intended Audience :: Developers
Requires-Python: >=3.8
License-File: LICENSE.md
Requires-Dist: importlib_resources; python_version < "3.9"
Requires-Dist: numpy>=1.20.0
Requires-Dist: tqdm
Provides-Extra: docs
Requires-Dist: sphinx_rtd_theme; extra == "docs"
Requires-Dist: nbsphinx>=0.8.6; extra == "docs"
Requires-Dist: Jinja2>=3.0.1; extra == "docs"
Requires-Dist: pandoc; extra == "docs"
Requires-Dist: ipython; extra == "docs"
Requires-Dist: jupyter; extra == "docs"
Provides-Extra: dev
Requires-Dist: cython>=0.29.16; extra == "dev"
Requires-Dist: pysen; extra == "dev"
Requires-Dist: types-setuptools; extra == "dev"
Requires-Dist: mypy<=0.910; extra == "dev"
Requires-Dist: black<=20.8,>=19.19b0; extra == "dev"
Requires-Dist: click<8.1.0; extra == "dev"
Requires-Dist: flake8<4,>=3.7; extra == "dev"
Requires-Dist: flake8-bugbear; extra == "dev"
Requires-Dist: isort<5.2.0,>=4.3; extra == "dev"
Requires-Dist: types-decorator; extra == "dev"
Requires-Dist: importlib-metadata<5.0; extra == "dev"
Provides-Extra: test
Requires-Dist: pytest; extra == "test"
Requires-Dist: scipy; extra == "test"
Provides-Extra: marine
Requires-Dist: marine>=0.0.5; extra == "marine"
Dynamic: license-file
